qubots/__init__.py
qubots/auto_optimizer.py
qubots/auto_problem.py
qubots/base_optimizer.py
qubots/base_problem.py
qubots/rastion_unified.py
qubots-1.1.6.dist-info/licenses/LICENSE
qubots-1.1.6.dist-info/METADATA
qubots-1.1.6.dist-info/WHEEL
qubots-1.1.6.dist-info/top_level.txt
qubots-1.1.6.dist-info/RECORD
