Metadata-Version: 2.4
Name: qubots
Version: 1.1.6
Summary: A collaborative optimization framework for creating optimization tools.
Author-email: "Ioannis D. Leonidas" <gleonidas303@gmail.com>
License:                                  Apache License
Project-URL: Homepage, https://rastion.com
Project-URL: Documentation, https://docs.rastion.com
Project-URL: Repository, https://github.com/Rastion/qubots
Project-URL: Bug Tracker, https://github.com/Rastion/qubots/issues
Project-URL: Changelog, https://github.com/Rastion/qubots/blob/main/CHANGELOG.md
Keywords: optimization,quantum,classical,community,operations-research,decision-variables,routing,scheduling,logistics,finance,energy
Classifier: Development Status :: 5 - Production/Stable
Classifier: Intended Audience :: Science/Research
Classifier: Intended Audience :: Developers
Classifier: Topic :: Scientific/Engineering :: Mathematics
Classifier: Topic :: Software Development :: Libraries :: Python Modules
Classifier: Programming Language :: Python :: 3
Classifier: Programming Language :: Python :: 3.9
Classifier: Programming Language :: Python :: 3.10
Classifier: Programming Language :: Python :: 3.11
Classifier: Programming Language :: Python :: 3.12
Classifier: License :: OSI Approved :: Apache Software License
Classifier: Operating System :: OS Independent
Requires-Python: >=3.9
License-File: LICENSE
Requires-Dist: typer>=0.9.0
Requires-Dist: requests>=2.28.0
Requires-Dist: python-dotenv>=0.19.0
Requires-Dist: numpy>=1.20.0
Requires-Dist: pandas>=1.3.0
Provides-Extra: routing
Requires-Dist: ortools>=9.0.0; extra == "routing"
Requires-Dist: matplotlib>=3.5.0; extra == "routing"
Provides-Extra: continuous
Requires-Dist: casadi>=3.5.0; extra == "continuous"
Requires-Dist: scipy>=1.7.0; extra == "continuous"
Provides-Extra: finance
Requires-Dist: cvxpy>=1.2.0; extra == "finance"
Requires-Dist: yfinance>=0.1.70; extra == "finance"
Requires-Dist: scipy>=1.7.0; extra == "finance"
Provides-Extra: energy
Requires-Dist: pyomo>=6.4.0; extra == "energy"
Requires-Dist: matplotlib>=3.5.0; extra == "energy"
Provides-Extra: fantasy-football
Requires-Dist: ortools>=9.0.0; extra == "fantasy-football"
Requires-Dist: matplotlib>=3.5.0; extra == "fantasy-football"
Requires-Dist: seaborn>=0.11.0; extra == "fantasy-football"
Provides-Extra: dev
Requires-Dist: pytest>=7.0.0; extra == "dev"
Requires-Dist: pytest-cov>=4.0.0; extra == "dev"
Requires-Dist: pytest-mock>=3.8.0; extra == "dev"
Requires-Dist: pytest-benchmark>=4.0.0; extra == "dev"
Requires-Dist: black>=22.0.0; extra == "dev"
Requires-Dist: isort>=5.10.0; extra == "dev"
Requires-Dist: flake8>=5.0.0; extra == "dev"
Requires-Dist: mypy>=0.991; extra == "dev"
Requires-Dist: pre-commit>=2.20.0; extra == "dev"
Requires-Dist: tox>=3.25.0; extra == "dev"
Requires-Dist: psutil>=5.8.0; extra == "dev"
Provides-Extra: test
Requires-Dist: pytest>=7.0.0; extra == "test"
Requires-Dist: pytest-cov>=4.0.0; extra == "test"
Requires-Dist: pytest-mock>=3.8.0; extra == "test"
Requires-Dist: pytest-benchmark>=4.0.0; extra == "test"
Requires-Dist: pytest-xdist>=2.5.0; extra == "test"
Requires-Dist: psutil>=5.8.0; extra == "test"
Provides-Extra: docs
Requires-Dist: sphinx>=5.0.0; extra == "docs"
Requires-Dist: sphinx-rtd-theme>=1.0.0; extra == "docs"
Requires-Dist: myst-parser>=0.18.0; extra == "docs"
Requires-Dist: sphinx-autodoc-typehints>=1.19.0; extra == "docs"
Provides-Extra: all
Requires-Dist: ortools>=9.0.0; extra == "all"
Requires-Dist: casadi>=3.5.0; extra == "all"
Requires-Dist: cvxpy>=1.2.0; extra == "all"
Requires-Dist: pyomo>=6.4.0; extra == "all"
Requires-Dist: yfinance>=0.1.70; extra == "all"
Requires-Dist: scipy>=1.7.0; extra == "all"
Requires-Dist: matplotlib>=3.5.0; extra == "all"
Requires-Dist: seaborn>=0.11.0; extra == "all"
Requires-Dist: jupyter>=1.0.0; extra == "all"
Dynamic: license-file
